{"ratings": 0.0, "userreviews": [], "description": "\u3010\u519b\u4e8b\u5f81\u6587\u7b2c\u4e00\u5b63\u00b7\u8840\u67d3\u7ea2\u65d7\u6218\u4e0d\u4f11\u3011\u53c2\u8d5b\u4f5c\u54c1", "title": "\u5927\u56fd\u53f2", "url": "https://book.qidian.com/info/1012260759", "average": -1.0, "cover": "//qidian.qpic.cn/qdbimg/349573/1012260759/180", "reviews": -1, "authors": [{"url": "https://me.qidian.com/authorIndex.aspx?id=402544590", "name": "\u516e\u65f8"}], "type": ["\u519b\u4e8b", "\u519b\u4e8b\u6218\u4e89"], "outlinks": ["https://book.qidian.com/info/1012260759", "https://book.qidian.com/info/33786", "https://book.qidian.com/info/33786", "https://book.qidian.com/info/38015", "https://book.qidian.com/info/38015", "https://book.qidian.com/info/78624", "https://book.qidian.com/info/78624", "https://book.qidian.com/info/140280", "https://book.qidian.com/info/140280", "https://book.qidian.com/info/146222", "https://book.qidian.com/info/146222", "https://book.qidian.com/info/152220", "https://book.qidian.com/info/152220", "https://book.qidian.com/info/1012257211", "https://book.qidian.com/info/1012257211", "https://book.qidian.com/info/1011773651", "https://book.qidian.com/info/1011792881", "https://book.qidian.com/info/1011766727", "https://book.qidian.com/info/1011816033", "https://book.qidian.com/info/1011910483", "https://book.qidian.com/info/1011695819", "https://book.qidian.com/info/1011962771", "https://book.qidian.com/info/1011786182", "https://book.qidian.com/info/1011837374", "https://book.qidian.com/info/1011724908"]}