{"ratings": 0.0, "userreviews": [{"userName": "~\u9aa8\u5c11", "userReviewDate": "2018-06-02", "userURL": "https://my.qidian.com/user/136065648", "userReview": "\u770b\u523043\u7ae0\uff0c\u770b\u4e0d\u4e0b\u53bb\u4e86"}, {"userName": "\u5415\u5929\u867e3558", "userReviewDate": "2018-05-27", "userURL": "https://my.qidian.com/user/313101724", "userReview": "\u7b7e\u5230\u652f\u6301\u4e00\u4e0b"}, {"userName": "\u5211\u5929\u5927\u5927\u54e6", "userReviewDate": "2018-05-17", "userURL": "https://my.qidian.com/user/211499823", "userReview": "\u611f\u89c9\u7cfb\u7edf\u70bc\u4e39\u90fd\u6709\u4e00\u4e2a\u901a\u75c5\uff0c\u5c31\u662f\u53ea\u4f1a\u70b9\u70b9\u70b9\uff0c\u4e00\u70b9\u4e5f\u4e0d\u4f1a\u836f\u6027\u548c\u5404\u79cd\u836f\u7269\u7684\u914d\u5408\uff0c\u53ea\u4f1a\u4e00\u5473\u7684\u70bc\u4e39"}, {"userName": "8\u65f6\u4ee38", "userReviewDate": "2018-04-16", "userURL": "https://my.qidian.com/user/225733629", "userReview": "\u2026\u501f\u9274\u7684\u5473\u9053"}, {"userName": "\u4f1dO\u661f\u8bed", "userReviewDate": "2018-03-08", "userURL": "https://my.qidian.com/user/211435909", "userReview": "\u9ed8\u9ed8\u5192\u4e2a\u6ce1_(:_\u300d\u2220)_"}, {"userName": "\u4e0d\u8272\u4e0d\u6deb", "userReviewDate": "2018-02-03", "userURL": "https://my.qidian.com/user/20676920", "userReview": "\u6bd2\u51fa\u8113 \u9876\u4e0d\u4f4f\u4e86"}, {"userName": "\u98ce@\u4f20\u4eba", "userReviewDate": "2018-01-31", "userURL": "https://my.qidian.com/user/2041005", "userReview": "\u8c01\u7ed9\u5267\u900f\u4e00\u4e0b\uff0c\u4e3b\u89d2\u540e\u9762\u6709\u6ca1\u6709\u7ee7\u7eed\u5446\u5728\u82cf\u5bb6"}, {"userName": "\u7231\u4ea6\u6216\u4e0d\u7231", "userReviewDate": "2018-01-26", "userURL": "https://my.qidian.com/user/213493321", "userReview": "\u770b\u5230\u6210\u5e74\u793c\u90a3\u90e8\u5206\u5c31\u770b\u4e0d\u4e0b\u53bb\u4e86\uff0c\u592a\u6076\u5fc3\u4e86"}, {"userName": "\u592f\u8298", "userReviewDate": "2018-01-16", "userURL": "https://my.qidian.com/user/224487519", "userReview": "\u73b0\u5728\u65e0\u654c\u6d41\u786e\u5b9e\u662f\u66f4\u53d7\u5927\u4f17\u559c\u6b22\uff0c\u56e0\u4e3a\u5f53\u5e74\u770b\u4e66\u7684\u4eba\u5dee\u4e0d\u591a\u90fd\u6b65\u5165\u4e86\u793e\u4f1a\uff0c\u4e0d\u50cf\u5b66\u751f\u65f6\u4ee3\u65e0\u5fe7\u65e0\u8651\u559c\u6b22"}, {"userName": "\u4e16\u840c\u6b87\u7d2b\u591c", "userReviewDate": "2018-01-15", "userURL": "https://my.qidian.com/user/156718851", "userReview": "\u4f5c\u8005\u4f60\u8fd9\u6709\u70b9\u60e8\u6de1\u554a\uff0c\u4e2a\u4eba\u89c9\u5f97\u5f88\u4e0d\u9519\uff0c\u4e0d\u77e5\u9053\u4e3a\u4ec0\u4e48\u6ca1\u6709\u8bc4\u8bba\u548c\u63a8\u8350\u7968\uff0c\u662f\u6211\u5361\u4e86\u5417\uff1f\u53cd\u6b63\u6211\u89c9\u5f97\u5199"}, {"userName": "\u56fd\u4ea7\u732b\u738b", "userReviewDate": "2017-12-07", "userURL": "https://my.qidian.com/user/199943867", "userReview": "\u6709\u4eba\u88ab\u6bd2\u6b7b\u6ca1"}, {"userName": "\u6e38\u606f", "userReviewDate": "2017-11-19", "userURL": "https://my.qidian.com/user/5796769", "userReview": "\u8be5\u6709\u7684\u4e0d\u8be5\u6709\u7684\u6bd2\u70b9\u4e00\u4e2a\u4e0d\u5dee\uff0c\u6015\u4e0d\u662f\u6bd2\u5230\u5410\u3002\u5e9f\u67f4\uff0c\u5bb6\u65cf\uff0c\u957f\u8001\u5b50\u5b59\uff0c\u5206\u5bb6\u5974\u4ec6\uff0c\u6210\u5e74\u6bd4\u6b66\u3002\u3002\u3002\u7b97"}, {"userName": "\u65e9\u4e59\u5973\u65b0\u4e4b\u52a9", "userReviewDate": "2017-11-08", "userURL": "https://my.qidian.com/user/199131240", "userReview": "\u8fd9\u672c\u4e66\u540d\u8981\u6211\u60f3\u5230\u4e00\u672c\u592a\u76d1\u7684\u4e66\uff0c\u4e00\u5f00\u59cb\u662f\u5151\u6362\u5e1d\u56fd\u65f6\u4ee3\u6e38\u620f\u5f00\u5c40\u5f02\u754c\uff0c\u540e\u9762\u662f\u9b54\u517d\u4e89\u9738\u5230\u866b\u65cf\u57fa\u5730\u3002"}, {"userName": "\u767d\u5200\u5207", "userReviewDate": "2017-10-06", "userURL": "https://my.qidian.com/user/308483866", "userReview": "\u6211\u6765\u8bf4\u8bf4\u6bcf\u65e5\u704c\u6c34\u7b7e\u5230"}], "description": "\u5fc3\u6f6e\u6f8e\u6e43\uff0c\u65e0\u9650\u5e7b\u60f3\uff0c\u8fce\u98ce\u6325\u51fb\u5343\u5c42\u6d6a\uff0c\u5c11\u5e74\u4e0d\u8d25\u70ed\u8840\uff01", "title": "\u5e26\u7740\u6e38\u620f\u7cfb\u7edf\u7eb5\u6a2a\u5f02\u4e16", "url": "https://book.qidian.com/info/1010330007", "average": -1.0, "cover": "//qidian.qpic.cn/qdbimg/349573/1010330007/180", "reviews": -1, "authors": [{"url": "https://me.qidian.com/authorIndex.aspx?id=400744611", "name": "\u9038\u6e21"}], "type": ["\u7384\u5e7b", "\u5f02\u4e16\u5927\u9646"], "outlinks": ["https://book.qidian.com/info/1010330007", "https://book.qidian.com/info/1010883866", "https://book.qidian.com/info/1010883866", "https://book.qidian.com/info/1009870272", "https://book.qidian.com/info/1009870272", "https://book.qidian.com/info/1010840437", "https://book.qidian.com/info/1010840437", "https://book.qidian.com/info/1010991284", "https://book.qidian.com/info/1010991284", "https://book.qidian.com/info/1010799783", "https://book.qidian.com/info/1010799783", "https://book.qidian.com/info/1010736832", "https://book.qidian.com/info/1010736832", "https://book.qidian.com/info/1011152383", "https://book.qidian.com/info/1011152383", "https://book.qidian.com/info/1011988403", "https://book.qidian.com/info/1009595922", "https://book.qidian.com/info/1011844784", "https://book.qidian.com/info/1011892497", "https://book.qidian.com/info/1011095320", "https://book.qidian.com/info/1011996851", "https://book.qidian.com/info/1011856434", "https://book.qidian.com/info/1011879207", "https://book.qidian.com/info/1011833256", "https://book.qidian.com/info/1011967674"]}