{"ratings": 0.0, "userreviews": [{"userName": "\u80d6\u5b50\u738b\u5b50", "userReviewDate": "2014-06-16", "userURL": "https://my.qidian.com/user/176702239", "userReview": "\u597d\u559c\u6b22\u8fd9\u672c\u5c0f\u8bf4\uff0c\u4e0d\u4e00\u6837\u7684\u7a7f\u8d8a\uff0c\u4e0d\u4e00\u6837\u7684\u723d\u6587\uff01\u8fd9\u672c\u4e66\u4e0d\u50cf\u522b\u7684\u5386\u53f2\u5c0f\u8bf4\u90a3\u6837\u67af\u71e5\uff0c\u5341\u5206\u7684\u8f7b\u677e\u52a0\u6109"}, {"userName": "\u5408\u683c\u5408\u683c\u4ee5\u540e", "userReviewDate": "2014-06-11", "userURL": "https://my.qidian.com/user/111699461", "userReview": "\u52a0\u6cb9\u66f4\u65b0\u554a\uff01\u4e13\u4e3a\u672c\u4e66\u8fdb\u884c\u5145\u503c\u4e86"}, {"userName": "\u539f\u6765\u540d\u5b57\u53ef\u4ee5\u8fd9\u4e48\u8d77\u554a", "userReviewDate": "2014-06-01", "userURL": "https://my.qidian.com/user/118166546", "userReview": "\u9996\u8ba2\u5fc5\u987b\u652f\u6301\u5440"}, {"userName": "\u65e0\u654c\u5207\u68a6\u5200", "userReviewDate": "2014-05-31", "userURL": "https://my.qidian.com/user/119093356", "userReview": "\u65e0\u8bc4\u8bba\uff0c\u4e0d\u8bfb\u4e66\uff01\u60a8\u7684\u8bc4\u8bba\u662f\u5bf9\u4f5c\u8005\u6700\u5927\u7684\u652f\u6301\uff0c\u8bf7\u5728\u6b64\u8f93\u5165\u60a8\u7684\u8bc4\u8bba\u5185\u5bb9"}, {"userName": "\u5fd8\u5fe7\u83492012", "userReviewDate": "3\u5c0f\u65f6\u524d", "userURL": "https://my.qidian.com/user/19981847", "userReview": "\u7b2c\u5341\u4e09\u7ae0\u53bb\u54ea\u91cc\u4e86\uff1f"}, {"userName": "\u4e2d\u7acb\u9635\u8425", "userReviewDate": "\u6628\u65e501:32", "userURL": "https://my.qidian.com/user/216477493", "userReview": "\u559c\u6b22\u6768\u5409\u513f\uff0c\u53ef\u60dc\u5979\u6ce8\u5b9a\u4e0d\u662f\u5973\u4e3b\u89d2"}, {"userName": "\u62db\u8d22\u732b\u7684\u732b", "userReviewDate": "2018-04-01", "userURL": "https://my.qidian.com/user/313296695", "userReview": "\u4f5c\u8005\u5927\u5927\u4e66\u597d\u770b\uff0c\u4e0d\u8fc7\u4e3a\u4ec0\u4e48\u597d\u591a\u7ae0\u90fd\u6ca1\u6709\u4e86\uff1f13.22.27.28.32.33.38.42."}, {"userName": "\u53d1\u5446\u72b6", "userReviewDate": "2018-03-31", "userURL": "https://my.qidian.com/user/212711851", "userReview": "\u7b2c\u5341\u4e09\u7ae0\u53bb\u54ea\u91cc\u4e86\uff1f"}, {"userName": "\u82b1\u843d\u706c\u6218\u6b4c", "userReviewDate": "2018-02-11", "userURL": "https://my.qidian.com/user/144061236", "userReview": "\u4f5c\u8005\u4f60\u53ea\u8981\u8bf4\u5c0f\u8bf4\u4e0d\u8981\u592a\u8ba4\u771f\u4e0d\u5c31\u884c\u4e86  \u81f3\u4e8e\u7816\u8def\u6211\u4f5c\u4e3a\u4e00\u4e2a\u5e72\u4e86\u4e09\u5e74\u5e02\u653f\u73af\u536b\u4e5f\u4fee\u8fc7\u8def\u7684\u53ef\u4ee5\u8d1f\u8d23"}, {"userName": "\u82b1\u5343\u6237", "userReviewDate": "2014-08-07", "userURL": "https://my.qidian.com/user/171404880", "userReview": "\u8fd9\u4e48\u597d\u7684\u5c0f\u8bf4\uff0c\u8d77\u70b9\u90fd\u4e0d\u7ed9\u4e00\u4e9b\u63a8\u8350\u652f\u6301\uff0c\u6574\u5929\u63a8\u8350\u90a3\u4e9b\u786c\u4f24\u4e00\u5927\u5806\u7684\u5c0f\u8bf4\u3002\u3002\u3002\u8fd9\u672c\u5c0f\u8bf4\u662f\u76ee\u524d\u5c11\u6570"}, {"userName": "\u88ab\u9057\u5f03\u7684\u86c0\u866b", "userReviewDate": "2014-08-05", "userURL": "https://my.qidian.com/user/100536338", "userReview": "\u8bf4\u5b9e\u8bdd\uff0c\u6211\u521a\u770b\u5230\u7816\u8def\u7684\u65f6\u5019\u4e5f\u662f\u6709\u4e00\u4e9b\u5410\u69fd\u7684\uff0c\u60f3\u6765\u8bc4\u8bba\uff0c\u7136\u540e\u5f03\u4e66\u800c\u53bb\uff0c\u5230\u4e86\u4e66\u8bc4\u533a\u5374\u53d1\u73b0\u5df2\u7ecf\u6709"}, {"userName": "\u82b1\u5343\u6237", "userReviewDate": "2014-08-05", "userURL": "https://my.qidian.com/user/171404880", "userReview": "[fn=2][fn=2][fn=2][fn=2][fn=2]"}, {"userName": "\u4e0a\u96c5", "userReviewDate": "2014-08-05", "userURL": "https://my.qidian.com/user/15066184", "userReview": "\u770b\u5230\u732a\u811a\u7528\u7816\u4fee\u8def\uff0c\u731b\u7136\u60ca\u5446\u4e86\uff0c\u8fd9\u662f\u5f02\u6b21\u5143\u7684\u661f\u7403\u5417\uff0c\u8fd9\u4e48\u7684\u7384\u5e7b\uff0c\u8d85\u51fa\u5730\u7403\u7684\u7269\u7406\u89c4\u5f8b\u4e86\uff0c\u770bZJ"}, {"userName": "$\u71d5\u660e\u84c9$", "userReviewDate": "2014-08-05", "userURL": "https://my.qidian.com/user/1553168", "userReview": "\u2018\u5510\u592a\u5b97\u8d1e\u89c2\u5e74\u95f4\u7269\u8d28\u6587\u660e\u6781\u5927\u4e30\u5bcc\uff0c\u4e00\u6597\u7c73\u53ea\u53565\u6587\u94b1\uff0c\u901a\u5e38\u4e00\u4e24\u94f6\u5b50\u62981000\u6587\u94dc\u94b1\uff08\u53c8\u79f0\u4e00\u8d2f"}], "description": "\u9192\u638c\u5929\u4e0b\u6743\uff0c\u9189\u5367\u7f8e\u4eba\u819d\uff0c\u4e94\u5343\u5e74\u98ce\u534e\u70df\u96e8\uff0c\u662f\u975e\u6210\u8d25\u8f6c\u5934\u7a7a\uff01", "title": "\u6211\u662f\u5080\u5121\u7687\u5e1d", "url": "https://book.qidian.com/info/3052578", "average": -1.0, "cover": "//qidian.qpic.cn/qdbimg/349573/3052578/180", "reviews": -1, "authors": [{"url": "https://me.qidian.com/authorIndex.aspx?id=3444673", "name": "\u5c06\u81e3\u4e00\u6012"}], "type": ["\u5386\u53f2", "\u4e24\u664b\u968b\u5510"], "outlinks": ["https://book.qidian.com/info/3052578", "https://book.qidian.com/info/1010308750", "https://book.qidian.com/info/1010308750", "https://book.qidian.com/info/1004947742", "https://book.qidian.com/info/1004947742", "https://book.qidian.com/info/1009441215", "https://book.qidian.com/info/1009441215", "https://book.qidian.com/info/2011044", "https://book.qidian.com/info/2011044", "https://book.qidian.com/info/1009391046", "https://book.qidian.com/info/1009391046", "https://book.qidian.com/info/1009727323", "https://book.qidian.com/info/1009727323", "https://book.qidian.com/info/3514773", "https://book.qidian.com/info/3514773", "https://book.qidian.com/info/3550516", "https://book.qidian.com/info/3550516", "https://book.qidian.com/info/1010361147", "https://book.qidian.com/info/1010361147", "https://book.qidian.com/info/1011800596", "https://book.qidian.com/info/1010891668", "https://book.qidian.com/info/1011773910", "https://book.qidian.com/info/1011783347", "https://book.qidian.com/info/1011643843", "https://book.qidian.com/info/1011476924", "https://book.qidian.com/info/1011635441", "https://book.qidian.com/info/1009999928", "https://book.qidian.com/info/1006932473", "https://book.qidian.com/info/1005080011"]}