{"ratings": 0.0, "userreviews": [{"userName": "\u4eba\u5c60\u4e07\u91cc", "userReviewDate": "2018-05-27", "userURL": "https://my.qidian.com/user/222759981", "userReview": "\u5148\u8bf4\u597d\u4f1a\u4e0d\u4f1a\u592a\u76d1\uff1f"}, {"userName": "\u9053\u9b42\u5929\u5c0a", "userReviewDate": "2018-05-20", "userURL": "https://my.qidian.com/user/200362723", "userReview": "\u6211\u4e5f\u6765\u4e00\u4e2a"}, {"userName": "k\u4e36\u5b9d\u5b9d", "userReviewDate": "2018-05-19", "userURL": "https://my.qidian.com/user/217655987", "userReview": "\u6253\u7834\u96f6\u8bc4\u8bba\uff0c\u5b89\u6170\u5b89\u6170\u4f60"}], "description": "\u661f\u6d77\u6f2b\u6e38\uff0c\u65f6\u7a7a\u7a7f\u68ad\uff0c\u673a\u68b0\u79d1\u6280\uff0c\u76ee\u6807\u662f\u672a\u77e5\u7684\u661f\u8fb0\u5927\u6d77\uff01", "title": "\u65e0\u9650\u7cfb\u7edf\u4e4b\u4e07\u52ab\u661f\u541b", "url": "https://book.qidian.com/info/1011828057", "average": -1.0, "cover": "//qidian.qpic.cn/qdbimg/349573/1011828057/180", "reviews": -1, "authors": [{"url": "https://me.qidian.com/authorIndex.aspx?id=402246180", "name": "\u51ac\u7720\u7684\u5c0f\u718a"}], "type": ["\u79d1\u5e7b", "\u65f6\u7a7a\u7a7f\u68ad"], "outlinks": ["https://book.qidian.com/info/1011828057", "https://book.qidian.com/info/1010691511", "https://book.qidian.com/info/1010691511", "https://book.qidian.com/info/1010800039", "https://book.qidian.com/info/1010800039", "https://book.qidian.com/info/1009810357", "https://book.qidian.com/info/1009810357", "https://book.qidian.com/info/1011261545", "https://book.qidian.com/info/1011261545", "https://book.qidian.com/info/1011281418", "https://book.qidian.com/info/1011281418", "https://book.qidian.com/info/1011301598", "https://book.qidian.com/info/1011301598", "https://book.qidian.com/info/1011814764", "https://book.qidian.com/info/1011636462", "https://book.qidian.com/info/1012011143", "https://book.qidian.com/info/1011989615", "https://book.qidian.com/info/1011979302", "https://book.qidian.com/info/1011962232", "https://book.qidian.com/info/1012020634", "https://book.qidian.com/info/1011923738", "https://book.qidian.com/info/1012020834", "https://book.qidian.com/info/1011973977"]}