{"ratings": 0.0, "userreviews": [{"userName": "\u58a8\u5ba2\u9526", "userReviewDate": "2017-06-20", "userURL": "https://my.qidian.com/user/224985315", "userReview": "\u76d6\u4e2a\u697c\uff0c\u4f1a\u6709\u4eba\u56de\u590d\u7b7e\u5230\u5417\uff1f"}, {"userName": "\u83b1\u6208\u62c9\u65af\uff5e\u98ce\u884c\u8005", "userReviewDate": "2018-04-13", "userURL": "https://my.qidian.com/user/210526921", "userReview": "\u770b\u5230\u8bcd\u4eba\u8fd9\u4e2a\u8bcd\u5c31\u77e5\u9053\u53ef\u4ee5\u4e0d\u7528\u770b\u4e86"}, {"userName": "\u6c5f\u6c34\u6a2a\u6ce2", "userReviewDate": "2018-04-10", "userURL": "https://my.qidian.com/user/131718087", "userReview": "\u8fd9\u4e2a\u6587\uff0c\u770b\u4e0d\u592a\u4e0b\u53bb\uff0c\u611f\u89c9\u6bd4\u8f83\u7cdf\u7cd5\u3002"}, {"userName": "\u9cb2\u9e4f3357", "userReviewDate": "2018-03-01", "userURL": "https://my.qidian.com/user/304694841", "userReview": "\u7b7e\u5230\u6c34\u7ecf\u9a8c"}, {"userName": "\u4e66\u53cb151229220634097", "userReviewDate": "2018-02-22", "userURL": "https://my.qidian.com/user/214091799", "userReview": "\u770b\u5230\u8fd9\u4e48\u591a\u9a82\u7684\uff0c\u6211\u5c31\u653e\u5fc3\u4e86[fn=4]"}, {"userName": "\u5546\u6d0b\u8001\u5927", "userReviewDate": "2018-02-15", "userURL": "https://my.qidian.com/user/212752382", "userReview": "\u611f\u89c9\u4e3b\u89d2\u597d\u50cf\u4e2a\u50bb\u5b50\uff0c\u518d\u6709\u4e66\u4e2d\u6b4c\u66f2\u7b49\u4f5c\u54c1\u8fc7\u4e8e\u5c0f\u4f17\uff0c\u65e0\u6cd5\u5e26\u6765\u4ee3\u5165\u611f\u7684\u8212\u723d\uff0c\u8df3\u770b\u4e86\u7231\u60c5\u516c\u5bd3\u4e00\u7ae0\uff0c"}, {"userName": "\u6d6e\u5938000", "userReviewDate": "2018-02-15", "userURL": "https://my.qidian.com/user/219224185", "userReview": "\u4e3a\u4ec0\u4e48\u53ea\u8bf4\u8bcd\u4f5c\u8005\u554a\uff1f\u8fd9\u8bcd\u672c\u8eab\u9009\u7684\u5c31\u90fd\u662f\u5931\u8d25\u54c1\uff0c\u8981\u597d\u66f2\u5b50\u886c\u6258\u624d\u6709\u4eba\u542c\u7684\u73a9\u610f\uff0c\u5149\u770b\u8fd9\u8bcd\u54ea\u6709\u4ec0\u4e48"}, {"userName": "\u51b0\u5170\u65e0\u5fc3", "userReviewDate": "2018-02-14", "userURL": "https://my.qidian.com/user/212399846", "userReview": "\u6211\u53ea\u60f3\u8bf4\u90a3\u5c06\u534e\u590f\u6b66\u529f\u63a8\u5e7f\u5230\u5168\u4e16\u754c\u7684\u4efb\u52a1\u5462\uff1f\u90a3\u4e00\u4e32\u4efb\u52a1\u7684\u5751\u90fd\u4e0d\u586b\u4e86\uff1f"}, {"userName": "\u8ff7\u5931\u3049\u661f\u7a7a", "userReviewDate": "2018-02-09", "userURL": "https://my.qidian.com/user/155701247", "userReview": "\u4f5c\u8005\u541b\uff0c\u8dc6\u62f3\u9053\u662f\u5357\u671d\u7684\uff0c\u67d4\u9053\u548c\u7a7a\u624b\u9053\u624d\u662f\u5c0f\u65e5\u672c\u7684"}, {"userName": "\u8001\u53f8\u673a\u5f00\u8f66\u4e86587", "userReviewDate": "2018-02-06", "userURL": "https://my.qidian.com/user/305876356", "userReview": "\u771f\u4e0d\u559c\u6b22\u7cfb\u7edf\u6587\uff0c\u597d\u5f71\u54cd\u610f\u5883\n"}, {"userName": "\u6843\u679d\u592d\u592di", "userReviewDate": "2018-01-18", "userURL": "https://my.qidian.com/user/227796173", "userReview": "\u732a\u811a\u5199\u7684\u8ddf\u5b59\u5b50\u4f3c\u5f97\uff0c\u89c1\u4eba\u5c31\u88ab\u8e29\uff0c\u53cd\u6297\u90fd\u6ca1\u6709\u3002"}, {"userName": "\u65e0\u5948\u7684\u661f", "userReviewDate": "2018-01-13", "userURL": "https://my.qidian.com/user/5532311", "userReview": "\u4e3a\u793c\u4eea\u4e4b\u90a6\u559d\u5f69\uff01"}, {"userName": "\u9648\u54c8\u54c8\u5475\u5475\u54c8\u54c8", "userReviewDate": "2018-01-05", "userURL": "https://my.qidian.com/user/212211075", "userReview": "\u4e2a\u4eba\u8bc4\u8bba\u697c"}, {"userName": "\u9634\u9633\u4e4b\u7ea6", "userReviewDate": "2018-01-03", "userURL": "https://my.qidian.com/user/221083587", "userReview": "\u86ee\u597d\u770b\u7684\uff0c\u4ecb\u610f\u6253\u5e7f\u544a\u4e0d\u2026\u2026\u4e00\u62f3\u5976\u7238\uff01\u6e29\u99a8\u671f\u5f85\u4f60\u7684\u5230\u6765\u3002"}], "description": "\u91cd\u751f\u8fc7\u53bb\u3001\u7545\u60f3\u672a\u6765\u3001\u68a6\u5e7b\u73b0\u5b9e\uff0c\u518d\u5851\u4f20\u5947\u4eba\u751f\uff01", "title": "\u8d85\u7ea7\u5de8\u661f\u5976\u7238", "url": "https://book.qidian.com/info/1009382033", "average": -1.0, "cover": "//qidian.qpic.cn/qdbimg/349573/1009382033/180", "reviews": -1, "authors": [{"url": "https://me.qidian.com/authorIndex.aspx?id=4311307", "name": "\u6e29\u4e03\u90ce"}], "type": ["\u90fd\u5e02", "\u5a31\u4e50\u660e\u661f"], "outlinks": ["https://book.qidian.com/info/1009382033", "https://book.qidian.com/info/1010812490", "https://book.qidian.com/info/1010812490", "https://book.qidian.com/info/1010901725", "https://book.qidian.com/info/1010901725", "https://book.qidian.com/info/1010806542", "https://book.qidian.com/info/1010806542", "https://book.qidian.com/info/1010629073", "https://book.qidian.com/info/1010629073", "https://book.qidian.com/info/1010925483", "https://book.qidian.com/info/1010925483", "https://book.qidian.com/info/1010811024", "https://book.qidian.com/info/1010811024", "https://book.qidian.com/info/3403593", "https://book.qidian.com/info/3403593", "https://book.qidian.com/info/1004146039", "https://book.qidian.com/info/1004146039", "https://book.qidian.com/info/1011932150", "https://book.qidian.com/info/1012029544", "https://book.qidian.com/info/1012015699", "https://book.qidian.com/info/1012018201", "https://book.qidian.com/info/1011879101", "https://book.qidian.com/info/1011790606", "https://book.qidian.com/info/1011971435", "https://book.qidian.com/info/1009695534", "https://book.qidian.com/info/1011890878", "https://book.qidian.com/info/1010537314"]}